cryptanalysis_tools/__init__.py
cryptanalysis_tools/crypto/utils.py
cryptanalysis_tools/crypto/asymmetric/sm2.py
cryptanalysis_tools/crypto/hash/length_extension_attack.py
cryptanalysis_tools/crypto/hash/sm3.py
cryptanalysis_tools/crypto/symmetric/modes.py
cryptanalysis_tools/crypto/symmetric/sm4.py
cryptanalysis_tools-0.1.4.dist-info/METADATA
cryptanalysis_tools-0.1.4.dist-info/WHEEL
cryptanalysis_tools-0.1.4.dist-info/licenses/LICENSE.txt
cryptanalysis_tools-0.1.4.dist-info/RECORD
