Metadata-Version: 2.4
Name: cryptanalysis_tools
Version: 0.1.4
Summary: sm crypto or more, cryptanalysis tools, toys
License-File: LICENSE.txt
Requires-Python: >=3.12
Requires-Dist: pycryptodome>=3.23.0
Requires-Dist: pycryptodomex>=3.23.0
Requires-Dist: sympy>=1.14.0
Requires-Dist: tinyec>=0.4.0
